cae/__init__.py
cae/cae.py
cae-0.4.dist-info/LICENSE
cae-0.4.dist-info/METADATA
cae-0.4.dist-info/WHEEL
cae-0.4.dist-info/top_level.txt
cae-0.4.dist-info/RECORD
