Metadata-Version: 2.1
Name: cae
Version: 0.4
Summary: A simple convolutional autoencoder
Home-page: https://github.com/jmmanley/conv-autoencoder
Author: Jason Manley
Author-email: jmanley@rockefeller.edu
License: GPLv3
Platform: UNKNOWN
Requires-Dist: keras
Requires-Dist: numpy
